
  [
    {
      "xpath": "/html[1]/body[1]/div[2]/div[3]/canvas[1]",
      "css": "#arrival canvas.marks",
      "event": "mousemove",
      "info": [
        389,
        170
      ],
      "task_id": 0
    },
    {
      "xpath": "/html[1]/body[1]/div[2]/div[3]/canvas[1]",
      "css": "#arrival canvas.marks",
      "event": "mouseout",
      "info": [
        -400,
        102
      ],
      "task_id": 0
    },
    {
      "xpath": "/html[1]/body[1]/div[2]/div[4]/canvas[1]",
      "css": "#departure canvas.marks",
      "event": "mousemove",
      "info": [
        298,
        102
      ],
      "task_id": 0
    },
    {
      "xpath": "/html[1]/body[1]/div[2]/div[4]/canvas[1]",
      "css": "#departure canvas.marks",
      "event": "mousemove",
      "info": [
        270,
        169
      ],
      "task_id": 0
    },
    {
      "xpath": "/html[1]/body[1]/div[2]/div[4]/canvas[1]",
      "css": "#departure canvas.marks",
      "event": "brush",
      "info": [
        272,
        50
      ],
      "task_id": 0
    },
    {
      "xpath": "/html[1]/body[1]/div[2]/div[4]/canvas[1]",
      "css": "#departure canvas.marks",
      "event": "brush",
      "info": [
        [
          [
            272,
            50
          ],
          [
            320,
            50
          ]
        ]
      ],
      "task_id": 0
    },
    {
      "xpath": "/html[1]/body[1]/div[2]/div[4]/canvas[1]",
      "css": "#departure canvas.marks",
      "event": "mouseout",
      "info": [
        666,
        208
      ],
      "task_id": 0
    },
    {
      "xpath": "/html[1]/body[1]/div[2]/div[2]/canvas[1]",
      "css": "#distance canvas.marks",
      "event": "mousemove",
      "info": [
        671,
        2
      ],
      "task_id": 0
    },
    {
      "xpath": "/html[1]/body[1]/div[2]/div[2]/canvas[1]",
      "css": "#distance canvas.marks",
      "event": "mouseout",
      "info": [
        778,
        167
      ],
      "task_id": 0
    },
    {
      "xpath": "/html[1]/body[1]/div[2]/div[6]/canvas[1]",
      "css": "#airtime canvas.marks",
      "event": "mousemove",
      "info": [
        80,
        167
      ],
      "task_id": 0
    },
    {
      "xpath": "/html[1]/body[1]/div[2]/div[6]/canvas[1]",
      "css": "#airtime canvas.marks",
      "event": "mouseout",
      "info": [
        388,
        279
      ],
      "task_id": 0
    },
    {
      "xpath": "/html[1]/body[1]/div[2]/div[6]/canvas[1]",
      "css": "#airtime canvas.marks",
      "event": "mouseout",
      "info": [
        -61,
        16
      ],
      "task_id": 0
    },
    {
      "xpath": "/html[1]/body[1]/div[2]/div[2]/canvas[1]",
      "css": "#distance canvas.marks",
      "event": "mouseout",
      "info": [
        430,
        -11
      ],
      "task_id": 0
    },
    {
      "xpath": "/html[1]/body[1]/div[2]/div[4]/canvas[1]",
      "css": "#departure canvas.marks",
      "event": "brush",
      "info": [
        [
          [
            272,
            50
          ],
          [
            370,
            50
          ]
        ]
      ],
      "task_id": 0
    },
    {
      "xpath": "/html[1]/body[1]/div[2]/div[4]/canvas[1]",
      "css": "#departure canvas.marks",
      "event": "mouseout",
      "info": [
        535,
        237
      ],
      "task_id": 0
    },
    {
      "xpath": "/html[1]/body[1]/div[2]/div[2]/canvas[1]",
      "css": "#distance canvas.marks",
      "event": "mouseout",
      "info": [
        1029,
        258
      ],
      "task_id": 0
    },
    {
      "xpath": "/html[1]/body[1]/div[2]/div[1]/canvas[1]",
      "css": "#count canvas.marks",
      "event": "mouseout",
      "info": [
        354,
        108
      ],
      "task_id": 0
    },
    {
      "xpath": "/html[1]/body[1]/div[2]/div[6]/canvas[1]",
      "css": "#airtime canvas.marks",
      "event": "mouseout",
      "info": [
        874,
        -44
      ],
      "task_id": 1
    },
    {
      "xpath": "/html[1]/body[1]/div[2]/div[6]/canvas[1]",
      "css": "#airtime canvas.marks",
      "event": "brush",
      "info": [
        [
          [
            272,
            50
          ],
          [
            502,
            50
          ]
        ]
      ],
      "task_id": 1
    },
    {
      "xpath": "/html[1]/body[1]/div[2]/div[6]/canvas[1]",
      "css": "#airtime canvas.marks",
      "event": "mouseout",
      "info": [
        533,
        215
      ],
      "task_id": 1
    },
    {
      "xpath": "/html[1]/body[1]/div[2]/div[1]/canvas[1]",
      "css": "#count canvas.marks",
      "event": "mouseout",
      "info": [
        306,
        140
      ],
      "task_id": 1
    },
    {
      "xpath": "/html[1]/body[1]/div[2]/div[6]/canvas[1]",
      "css": "#airtime canvas.marks",
      "event": "mouseout",
      "info": [
        951,
        41
      ],
      "task_id": 2
    },
    {
      "xpath": "/html[1]/body[1]/div[2]/div[3]/canvas[1]",
      "css": "#arrival canvas.marks",
      "event": "mouseout",
      "info": [
        689,
        170
      ],
      "task_id": 2
    },
    {
      "xpath": "/html[1]/body[1]/div[2]/div[7]/canvas[1]",
      "css": "#delay canvas.marks",
      "event": "mousemove",
      "info": [
        301,
        280
      ],
      "task_id": 2
    },
    {
      "xpath": "/html[1]/body[1]/div[2]/div[7]/canvas[1]",
      "css": "#delay canvas.marks",
      "event": "mouseout",
      "info": [
        606,
        398
      ],
      "task_id": 2
    },
    {
      "xpath": "/html[1]/body[1]/div[2]/div[1]/canvas[1]",
      "css": "#count canvas.marks",
      "event": "mouseout",
      "info": [
        450,
        -20
      ],
      "task_id": 3
    },
    {
      "xpath": "/html[1]/body[1]/div[2]/div[3]/canvas[1]",
      "css": "#arrival canvas.marks",
      "event": "mouseout",
      "info": [
        -10,
        86
      ],
      "task_id": 3
    },
    {
      "xpath": "/html[1]/body[1]/div[2]/div[4]/canvas[1]",
      "css": "#departure canvas.marks",
      "event": "mouseout",
      "info": [
        275,
        244
      ],
      "task_id": 3
    },
    {
      "xpath": "/html[1]/body[1]/div[2]/div[2]/canvas[1]",
      "css": "#distance canvas.marks",
      "event": "mouseout",
      "info": [
        291,
        324
      ],
      "task_id": 3
    },
    {
      "xpath": "/html[1]/body[1]/div[2]/div[7]/canvas[1]",
      "css": "#delay canvas.marks",
      "event": "mouseout",
      "info": [
        746,
        353
      ],
      "task_id": 3
    },
    {
      "xpath": "/html[1]/body[1]/div[2]/div[1]/canvas[1]",
      "css": "#count canvas.marks",
      "event": "mouseout",
      "info": [
        722,
        -8
      ],
      "task_id": 3
    },
    {
      "xpath": "/html[1]/body[1]/div[2]/div[6]/canvas[1]",
      "css": "#airtime canvas.marks",
      "event": "mouseout",
      "info": [
        341,
        646
      ],
      "task_id": 3
    },
    {
      "xpath": "/html[1]/body[1]/div[2]/div[6]/canvas[1]",
      "css": "#airtime canvas.marks",
      "event": "mouseout",
      "info": [
        349,
        642
      ],
      "task_id": 4
    }
  ]
